pyiBook/__init__.py
pyiBook/commands.py
pyiBook/display.py
pyiBook/poccess.py
pyiBook-1.0.1.dist-info/LICENSE
pyiBook-1.0.1.dist-info/METADATA
pyiBook-1.0.1.dist-info/WHEEL
pyiBook-1.0.1.dist-info/entry_points.txt
pyiBook-1.0.1.dist-info/top_level.txt
pyiBook-1.0.1.dist-info/RECORD
