Metadata-Version: 2.1
Name: pyiBook
Version: 1.0.1
Summary: A CLI tool for interacting with iBooks library.
Author-email: Tess <bingting01@outlook.com>
License: Copyright (c) [2024] [BINGTINGHUANGFU]
Project-URL: Homepage, https://github.com/higher-bottle/pyiBook
Project-URL: Issues, https://github.com/higher-bottle/pyiBook/issues
Classifier: Programming Language :: Python :: 3
Classifier: License :: OSI Approved :: MIT License
Classifier: Operating System :: OS Independent
Requires-Python: >=3.9
License-File: LICENSE
Requires-Dist: Click
Requires-Dist: rich
Requires-Dist: pandas
Requires-Dist: requests
Requires-Dist: openpyxl
